LICENSE
MANIFEST.in
README.md
setup.cfg
setup.py
cwl_airflow/__init__.py
cwl_airflow/git_version
cwl_airflow.egg-info/PKG-INFO
cwl_airflow.egg-info/SOURCES.txt
cwl_airflow.egg-info/dependency_links.txt
cwl_airflow.egg-info/not-zip-safe
cwl_airflow.egg-info/requires.txt
cwl_airflow.egg-info/top_level.txt
cwl_airflow/bin/__init__.py
cwl_airflow/bin/cwl-airflow
cwl_airflow/components/__init__.py
cwl_airflow/components/api/__init__.py
cwl_airflow/components/api/backend.py
cwl_airflow/components/api/server.py
cwl_airflow/components/api/openapi/swagger_configuration.yaml
cwl_airflow/components/init/__init__.py
cwl_airflow/components/init/config.py
cwl_airflow/components/test/__init__.py
cwl_airflow/components/test/conformance.py
cwl_airflow/config_templates/__init__.py
cwl_airflow/config_templates/airflow_local_settings.py
cwl_airflow/data/default_simulation_suite.yaml
cwl_airflow/extensions/__init__.py
cwl_airflow/extensions/cwldag.py
cwl_airflow/extensions/dags/__init__.py
cwl_airflow/extensions/dags/clean_dag_run.py
cwl_airflow/extensions/operators/__init__.py
cwl_airflow/extensions/operators/cwljobdispatcher.py
cwl_airflow/extensions/operators/cwljobgatherer.py
cwl_airflow/extensions/operators/cwlstepoperator.py
cwl_airflow/utilities/__init__.py
cwl_airflow/utilities/cwl.py
cwl_airflow/utilities/helpers.py
cwl_airflow/utilities/loggers.py
cwl_airflow/utilities/parser.py
cwl_airflow/utilities/report.py
cwl_airflow/utilities/simulation.py