Metadata-Version: 2.1
Name: cwl-airflow
Version: 1.2.11
Summary: Python package to extend Airflow functionality with CWL v1.1 support
Home-page: https://github.com/Barski-lab/cwl-airflow
Author: Michael Kotliar
Author-email: misha.kotliar@gmail.com
License: Apache-2.0
Download-URL: https://github.com/Barski-lab/cwl-airflow
Platform: UNKNOWN
Classifier: Development Status :: 5 - Production/Stable
Classifier: Environment :: Console
Classifier: Environment :: Other Environment
Classifier: Intended Audience :: Developers
Classifier: Intended Audience :: Science/Research
Classifier: Intended Audience :: Healthcare Industry
Classifier: License :: OSI Approved :: Apache Software License
Classifier: Natural Language :: English
Classifier: Operating System :: MacOS :: MacOS X
Classifier: Operating System :: POSIX
Classifier: Operating System :: POSIX :: Linux
Classifier: Operating System :: OS Independent
Classifier: Programming Language :: Python :: 3.7
Classifier: Topic :: Scientific/Engineering
Classifier: Topic :: Scientific/Engineering :: Bio-Informatics
Classifier: Topic :: Scientific/Engineering :: Chemistry
Classifier: Topic :: Scientific/Engineering :: Information Analysis
Classifier: Topic :: Scientific/Engineering :: Medical Science Apps.
Provides-Extra: celery
Provides-Extra: mysql
Provides-Extra: statsd
Provides-Extra: rabbitmq
Provides-Extra: postgres
License-File: LICENSE
